[
    {
        "num":  "001",
        "folder":  "001-talamus-card-grid",
        "title":  "Talamus 错位卡片网格",
        "subtitle":  "staggered card grid",
        "description":  "7 张白色卡片用 grid + nth-child(8n+k) translateY/translateX 错位排布；每张卡的 scale + opacity 由独立 IntersectionObserver 触发，所以滚动到位会陆续出现而非一次全显；同时叠加 simpleparallax-js 的连续滚动 drift（每张卡 scale 1.0 + index*0.2，速率不同制造层次）。源自 Talamus 首页 \"formations\" section。",
        "tech":  "CSS Grid + IO + simpleparallax-js",
        "tags":  [
                     "animation",
                     "intro",
                     "scroll"
                 ],
        "previewHref":  "",
        "sourceUrl":  "https://talamus.pro/",
        "localMirror":  "../designs/001-talamus/index.html",
        "order":  1
    },
    {
        "num":  "002",
        "folder":  "002-talamus-hero",
        "title":  "Talamus Hero（Himax 定制版）",
        "subtitle":  "video bg + char-by-char title reveal",
        "description":  "Talamus 首页 hero 1:1 还原：橙色粒子背景视频铺满，超大标题用 splitting.js 拆字母后逐个 translateY 上滑（per-char-delay = char-index × 10ms）；CTA 带白块右扩 + 箭头旋转 hover；右下角说明配竖线 0%→100% + 文字 translateX 滑入。Tadam 类在 window load 后 10ms 一次性给所有 [data-tadam] 加 --tadam 触发动画。已替换文案为「阿祖AI建站」+ 左上角 Himax 品牌标，字体改用 Inter 800（halyard-display 是 Adobe Typekit 私有授权，离线 fallback 系统 bold sans）。",
        "tech":  "splitting.js + CSS transitions",
        "tags":  [
                     "animation",
                     "intro",
                     "typography",
                     "hero"
                 ],
        "previewHref":  "",
        "sourceUrl":  "https://talamus.pro/",
        "localMirror":  "../designs/001-talamus/index.html",
        "order":  2
    },
    {
        "num":  "003",
        "folder":  "003-talamus-cta",
        "title":  "Talamus CTA",
        "subtitle":  "scroll-trigger char reveal over particle video",
        "description":  "Talamus 中段 CTA：黑底红色粒子视频铺满，标题用 splitting.js 拆字母后逐个 translateY 上滑（per-char-delay = char-index × 10ms），跟着 0.5s opacity 淡出橙色 CTA 按钮（带白块右扩 + 箭头旋转 hover）。整段由 TadamScroll 监听滚动位置，scrollY+innerHeight 越过 section 绝对顶时给 .module-cta 加 --tadam，连锁触发标题字符 + CTA 反复。完全 1:1 还原原版交互。",
        "tech":  "splitting.js + scroll trigger",
        "tags":  [
                     "animation",
                     "intro",
                     "scroll",
                     "typography"
                 ],
        "previewHref":  "",
        "sourceUrl":  "https://talamus.pro/",
        "localMirror":  "../designs/001-talamus/index.html",
        "order":  3
    },
    {
        "num":  "004",
        "folder":  "004-shift5-categories",
        "title":  "Shift5 分类卡片 hover",
        "subtitle":  "4-column slider with coral hover takeover",
        "description":  "Shift5 中段产品分类区：横向 4 卡片 grid，每卡 48rem 宽（~480px @1440px），细线边框由 4 个 absolute 定位的 ::line 元素拼出。鼠标 hover 时卡片整体变珊瑚红 #ff5841、Explore 按钮反相（黑底珊瑚字），0.2s ease 过渡。每张卡片有独特 SVG 图标（地球线框 / 半色调圆点 / 星芒 / 立方体）。顶部带左右 slider 箭头控件，点击 scrollBy 一格。",
        "tech":  "CSS Grid + SVG sprite + scroll snap",
        "tags":  [
                     "interaction",
                     "animation"
                 ],
        "previewHref":  "",
        "sourceUrl":  "https://shift5.io/",
        "localMirror":  "../designs/002-shift5/index.html",
        "order":  4
    },
    {
        "num":  "005",
        "folder":  "005-shift5-news",
        "title":  "Shift5 新闻列表 sticky 双栏",
        "subtitle":  "sticky featured panel + scrolling article grid",
        "description":  "Shift5 的 newsroom 区：左侧黑底特色文章面板（图片 + 标题 + 日期 + 描述 + READ MORE 按钮）做 sticky；右侧灰底 2 列 grid 排 12 篇文章卡片，鼠标 hover 卡片整体翻转成黑底浅字（0.4s ease-in-out）。原版用 JS scroll listener + transform 实现 sticky，我们用 CSS position: sticky 等价替换。每张卡片用 absolute 定位的细线（item-line[data-line=x|y]）拼出格子边框。",
        "tech":  "CSS Grid + position: sticky",
        "tags":  [
                     "interaction",
                     "scroll"
                 ],
        "previewHref":  "",
        "sourceUrl":  "https://shift5.io/",
        "localMirror":  "../designs/002-shift5/index.html",
        "order":  5
    }
]